sqlcli/__init__.py
sqlcli/commandanalyze.py
sqlcli/datawrapper.py
sqlcli/hdfswrapper.py
sqlcli/main.py
sqlcli/sqlcli.py
sqlcli/sqlcliexception.py
sqlcli/sqlclijdbcapi.py
sqlcli/sqlclijobmanager.py
sqlcli/sqlclimeta.py
sqlcli/sqlclitransactionmanager.py
sqlcli/sqlexecute.py
sqlcli/sqloption.py
sqlcli/sqlparse.py
sqlcli/sshwrapper.py
sqlcli/testwrapper.py
sqlcli/conf/sqlcli.ini
sqlcli/jlib/README
sqlcli/profile/default
robotslacker_sqlcli_noodbc-0.0.4.dist-info/LICENSE.txt
robotslacker_sqlcli_noodbc-0.0.4.dist-info/METADATA
robotslacker_sqlcli_noodbc-0.0.4.dist-info/WHEEL
robotslacker_sqlcli_noodbc-0.0.4.dist-info/entry_points.txt
robotslacker_sqlcli_noodbc-0.0.4.dist-info/top_level.txt
robotslacker_sqlcli_noodbc-0.0.4.dist-info/RECORD
