Metadata-Version: 2.1
Name: robotslacker-sqlcli-noodbc
Version: 0.0.4
Summary: SQL Command test tool, use JDBC
Home-page: https://github.com/robotslacker/sqlcli
Author: RobotSlacker
Author-email: 184902652@qq.com
License: UNKNOWN
Keywords: sql command test tool
Platform: any
Requires-Python: >=3.6
Requires-Dist: JPype1
Requires-Dist: setproctitle
Requires-Dist: pathlib
Requires-Dist: urllib3
Requires-Dist: pyparsing
Requires-Dist: click
Requires-Dist: prompt-toolkit
Requires-Dist: fs
Requires-Dist: hdfs
Requires-Dist: wget
Requires-Dist: httptools
Requires-Dist: pika
Requires-Dist: paramiko
Requires-Dist: numpy
